Metadata-Version: 2.1
Name: pdcoder-start-update
Version: 0.3.0
Summary: A visual data manipulation tool that automatically generates python code
Home-page: https://gitee.com/carson_add/pandas-ui
Author: Carson Liang
Author-email: 568166495@qq.com
License: MIT
Platform: UNKNOWN
Classifier: License :: OSI Approved :: MIT License
Classifier: Programming Language :: Python
Classifier: Programming Language :: Python :: 3
Classifier: Programming Language :: Python :: 3.6
Classifier: Programming Language :: Python :: Implementation :: CPython
Classifier: Programming Language :: Python :: Implementation :: PyPy
Requires-Python: >=3.6.0
